jpm_online_payments/__init__.py
jpm_online_payments/client.py
jpm_online_payments/core/__init__.py
jpm_online_payments/core/api_error.py
jpm_online_payments/core/auth.py
jpm_online_payments/core/base_client.py
jpm_online_payments/core/binary_response.py
jpm_online_payments/core/request.py
jpm_online_payments/core/response.py
jpm_online_payments/core/type_utils.py
jpm_online_payments/core/utils.py
jpm_online_payments/environment.py
jpm_online_payments/resources/captures/README.md
jpm_online_payments/resources/captures/__init__.py
jpm_online_payments/resources/captures/client.py
jpm_online_payments/resources/fraudcheck/README.md
jpm_online_payments/resources/fraudcheck/__init__.py
jpm_online_payments/resources/fraudcheck/client.py
jpm_online_payments/resources/healthcheck/README.md
jpm_online_payments/resources/healthcheck/__init__.py
jpm_online_payments/resources/healthcheck/client.py
jpm_online_payments/resources/payments/README.md
jpm_online_payments/resources/payments/__init__.py
jpm_online_payments/resources/payments/captures/README.md
jpm_online_payments/resources/payments/captures/__init__.py
jpm_online_payments/resources/payments/captures/client.py
jpm_online_payments/resources/payments/client.py
jpm_online_payments/resources/refunds/README.md
jpm_online_payments/resources/refunds/__init__.py
jpm_online_payments/resources/refunds/client.py
jpm_online_payments/resources/verifications/README.md
jpm_online_payments/resources/verifications/__init__.py
jpm_online_payments/resources/verifications/client.py
jpm_online_payments/types/models/__init__.py
jpm_online_payments/types/models/account_holder.py
jpm_online_payments/types/models/account_updater.py
jpm_online_payments/types/models/ach.py
jpm_online_payments/types/models/additional_data.py
jpm_online_payments/types/models/address.py
jpm_online_payments/types/models/alipay.py
jpm_online_payments/types/models/applepay.py
jpm_online_payments/types/models/application_info.py
jpm_online_payments-0.1.0.dist-info/METADATA
jpm_online_payments-0.1.0.dist-info/WHEEL
jpm_online_payments-0.1.0.dist-info/RECORD
